Metadata-Version: 1.1
Name: palpyutil
Version: 0.0.1
Summary: Fast matching of source-sharing derivative time series.
Home-page: https://github.com/shaypal5/palpyutil
Author: Shay Palachy
Author-email: shaypal5@gmail.com
License: MIT
Keywords: pandas dataframe pipeline data
Platform: any
Classifier: Development Status :: 4 - Beta
Classifier: License :: OSI Approved :: MIT License
Classifier: Programming Language :: Python
Classifier: Programming Language :: Python :: 3.5
Classifier: Programming Language :: Python :: 3.6
Classifier: Topic :: Software Development :: Libraries
Classifier: Topic :: Software Development :: Libraries :: Python Modules
Classifier: Intended Audience :: Developers
